setup.py
svm/__init__.py
svm/spark.py
svm.egg-info/PKG-INFO
svm.egg-info/SOURCES.txt
svm.egg-info/dependency_links.txt
svm.egg-info/not-zip-safe
svm.egg-info/requires.txt
svm.egg-info/top_level.txt