Metadata-Version: 1.0
Name: svm
Version: 0.0.0
Summary: Version manager for Apache Spark
Home-page: http://nedappjira001.int.asurion.com:8990/scm/gsa/retail_toolkit.git
Author: Chris Kirby
Author-email: kirbycm@gmail.com
License: MIT
Platform: UNKNOWN
